jsalesforce.py
jsalesforce-0.3.3.dist-info/METADATA
jsalesforce-0.3.3.dist-info/WHEEL
jsalesforce-0.3.3.dist-info/top_level.txt
jsalesforce-0.3.3.dist-info/RECORD
