Metadata-Version: 2.1
Name: jsalesforce
Version: 0.3.3
Summary: This package contains useful functions to extract data and write data to Salesforce. It is designed for ETH juniors only
Home-page: https://github.com/
Author: Frederik Semmel
Author-email: frederiksemmel@gmail.com
License: UNKNOWN
Platform: UNKNOWN
Classifier: Programming Language :: Python :: 3
Classifier: Programming Language :: Python :: 3.6
Classifier: License :: OSI Approved :: MIT License
Classifier: Operating System :: OS Independent
Requires-Python: >=3.6
Requires-Dist: pandas (>=1.0)
Requires-Dist: simple-salesforce (>=0.25.3)
